reportforce/__init__.py
reportforce/api.py
reportforce/login.py
reportforce/helpers/__init__.py
reportforce/helpers/errors.py
reportforce/helpers/matrix.py
reportforce/helpers/metadata.py
reportforce/helpers/parsers.py
reportforce/helpers/report.py
reportforce/helpers/summary.py
reportforce/helpers/tabular.py
reportforce/helpers/utils.py
reportforce/helpers/xml.py
reportforce-0.0.7.dist-info/METADATA
reportforce-0.0.7.dist-info/WHEEL
reportforce-0.0.7.dist-info/top_level.txt
reportforce-0.0.7.dist-info/RECORD
