Metadata-Version: 2.1
Name: reportforce
Version: 0.0.7
Summary: A Salesforce Analytics API client for Python
Home-page: https://github.com/phelipetls/reportforce
Author: Phelipe Teles
Author-email: phelipe_teles@hotmail.com
License: UNKNOWN
Project-URL: Documentation, https://reportforce.readthedocs.io/
Platform: UNKNOWN
Classifier: Programming Language :: Python :: 3
Classifier: License :: OSI Approved :: MIT License
Classifier: Operating System :: OS Independent
Requires-Python: >=3.6
Requires-Dist: pandas
Requires-Dist: requests
